amber/__init__.py
amber/getter.py
amber/wrapper.py
amber/architect/__init__.py
amber/architect/base.py
amber/architect/buffer.py
amber/architect/commonOps.py
amber/architect/manager.py
amber/architect/modelSpace.py
amber/architect/reward.py
amber/architect/store.py
amber/architect/trainEnv.py
amber/architect/optim/__init__.py
amber/architect/optim/controller/__init__.py
amber/architect/optim/controller/base.py
amber/architect/optim/controller/controllerTrainEnv.py
amber/architect/optim/controller/pytorch/__init__.py
amber/architect/optim/controller/pytorch/generalController.py
amber/architect/optim/controller/tf1/__init__.py
amber/architect/optim/controller/tf1/generalController.py
amber/architect/optim/controller/tf1/multiioController.py
amber/architect/optim/controller/tf1/operationController.py
amber/architect/optim/controller/tf1/zeroShotController.py
amber/architect/optim/controller/tf2/__init__.py
amber/architect/optim/controller/tf2/generalController.py
amber/architect/optim/pmbga/__init__.py
amber/architect/optim/pmbga/bayes_prob.py
amber/architect/optim/pmbga/genetic_algo.py
amber/backend/__init__.py
amber/backend/amber_ops.py
amber/backend/backend.py
amber/backend/set_default_backend.py
amber/backend/pytorch/__init__.py
amber/backend/pytorch/cache.py
amber/backend/pytorch/layer.py
amber/backend/pytorch/math.py
amber/backend/pytorch/model.py
amber/backend/pytorch/session.py
amber/backend/pytorch/tensor.py
amber/backend/pytorch/utils.py
amber/backend/tensorflow_1/__init__.py
amber/backend/tensorflow_1/math.py
amber/backend/tensorflow_1/model.py
amber/backend/tensorflow_1/session.py
amber/backend/tensorflow_1/tensor.py
amber/backend/tensorflow_1/_operators/__init__.py
amber/backend/tensorflow_1/_operators/denovo_motif_conv.py
amber/backend/tensorflow_1/_operators/sepfc.py
amber/backend/tensorflow_1/_operators/topk.py
amber/backend/tensorflow_2/__init__.py
amber/backend/tensorflow_2/cache.py
amber/backend/tensorflow_2/math.py
amber_automl-0.1.5.dist-info/LICENSE
amber_automl-0.1.5.dist-info/METADATA
amber_automl-0.1.5.dist-info/WHEEL
amber_automl-0.1.5.dist-info/top_level.txt
amber_automl-0.1.5.dist-info/RECORD
